wikipyedia_md/__init__.py
wikipyedia_md/html_filtering.py
wikipyedia_md/main.py
wikipyedia_md/wiki_parser.py
wikipyedia_md-0.1.0.dist-info/LICENSE.md
wikipyedia_md-0.1.0.dist-info/METADATA
wikipyedia_md-0.1.0.dist-info/WHEEL
wikipyedia_md-0.1.0.dist-info/RECORD
