Metadata-Version: 2.1
Name: wikipyedia-md
Version: 0.1.0
Summary: Package made for converting Wikipedia articles to Markdown format
License: MIT
Author: Edvinas Adomaitis
Author-email: t4skmanag3r@gmail.com
Requires-Python: >=3.10,<4.0
Classifier: License :: OSI Approved :: MIT License
Classifier: Programming Language :: Python :: 3
Classifier: Programming Language :: Python :: 3.10
Classifier: Programming Language :: Python :: 3.11
Requires-Dist: beautifulsoup4 (>=4.12.2,<5.0.0)
Requires-Dist: requests (>=2.31.0,<3.0.0)
